tiny_router/__init__.py
tiny_router/exceptions.py
tiny_router/py.typed
tiny_router/router.py
tiny_router/simple.py
tiny_router/simple_regex/__init__.py
tiny_router/simple_regex/mapping.py
tiny_router/simple_regex/resource_resolver.py
tiny_router/simple_regex/router.py
tiny_router-0.0.8.dist-info/LICENSE
tiny_router-0.0.8.dist-info/WHEEL
tiny_router-0.0.8.dist-info/METADATA
tiny_router-0.0.8.dist-info/RECORD
