Metadata-Version: 2.1
Name: tiny-router
Version: 0.0.8
Summary: Tiny HTTP router
Home-page: https://github.com/nekonoshiri/tiny-router
License: MIT
Keywords: router
Author: Shiri Nekono
Author-email: gexira.halen.toms@gmail.com
Maintainer: Shiri Nekono
Maintainer-email: gexira.halen.toms@gmail.com
Requires-Python: >=3.7.2,<4.0.0
Classifier: Development Status :: 1 - Planning
Classifier: Intended Audience :: Developers
Classifier: License :: OSI Approved :: MIT License
Classifier: Programming Language :: Python :: 3
Classifier: Programming Language :: Python :: 3.8
Classifier: Programming Language :: Python :: 3.9
Classifier: Topic :: Internet :: WWW/HTTP :: HTTP Servers
Classifier: Topic :: Software Development :: Libraries
Requires-Dist: typing-extensions (>=3.7.4,<4.0.0)
Project-URL: Documentation, https://github.com/nekonoshiri/tiny-router
Project-URL: Repository, https://github.com/nekonoshiri/tiny-router
